[{"id":1762336293610,"workplace":"bjmilv","name":"¸","phone":"¢¨¡°©"},{"id":1762336293611,"workplace":"bjmi˩","name":"¸","phone":"¢¥§«¬"},{"id":1762336293612,"workplace":"bjmi","name":"¸","phone":"¢§¥£ª§"},{"id":1762336293613,"workplace":"bjmiѫ","name":"¸","phone":"¢¤¢­§"},{"id":1762336293614,"workplace":"bjmƥl","name":"¸","phone":"¢©§ª«"},{"id":1762336293615,"workplace":"bjґil","name":"¸","phone":"¢¦®ª"},{"id":1762336293616,"workplace":"bjmilv","name":"¸","phone":"¢©§ª«"},{"id":1762336293617,"workplace":"ǜjתi","name":"¸","phone":"¥©¡§°£"},{"id":1762336293618,"workplace":"bjmilv","name":"¸","phone":"¢£ ¨±¨"},{"id":1762336293619,"workplace":"bj큫i","name":"¸","phone":"¢¤¡¢°ª"},{"id":1762336293620,"workplace":"bjӗil","name":"¸","phone":"¢£¢¯©"},{"id":1762336293621,"workplace":"bjmi","name":"¸","phone":"¢£¥°£"},{"id":1762336293622,"workplace":"bjmilv","name":"¸","phone":"¢©¤®©"},{"id":1762336293623,"workplace":"؈jmil","name":"¸","phone":"¢£§«§"},{"id":1762336293624,"workplace":"bjmil","name":"¸","phone":"¢§¡°¥"},{"id":1762336293625,"workplace":"bjաil","name":"¸","phone":"¢©£²¬"},{"id":1762336293626,"workplace":"bjmȩ","name":"¸","phone":"¢©¢®ª"},{"id":1762336293627,"workplace":"Ģjmţ","name":"¸","phone":"¢¨¤²¬"},{"id":1762336293628,"workplace":"đҎmi","name":"¸","phone":"¢©£²«"},{"id":1762336293629,"workplace":"bקm","name":"¸","phone":"¢©§ª§"},{"id":1762336293630,"workplace":"bjŧil","name":"¸","phone":"¥©¡§°©"},{"id":1762336293631,"workplace":"֑jmil","name":"¸","phone":"¢£¥±¦"},{"id":1762336293632,"workplace":"bjmil","name":"¸","phone":"¢¤®£"},{"id":1762336293633,"workplace":"bjmilv","name":"¸","phone":"¥¨¢®«"},{"id":1762336293634,"workplace":"bjmilv","name":"¸","phone":"¥££¥©¤"},{"id":1762336293636,"workplace":"bjґil","name":"¸","phone":"¢£ª¤"},{"id":1762336293637,"workplace":"bĬmӢ","name":"¸","phone":"¢§¡°¨"},{"id":1762336293638,"workplace":"bjmiȬ","name":"¸","phone":"¢¨¡°¬"},{"id":1762336293639,"workplace":"bjmiȫ","name":"¸","phone":"¢§¥°¤"},{"id":1762336293640,"workplace":"bjґil","name":"¸","phone":"¢£¥²©"},{"id":1762336293641,"workplace":"bjmilv","name":"¸","phone":"¢¨£°£"},{"id":1762336293642,"workplace":"bjmi","name":"¸","phone":"¢¨¤²¤"},{"id":1762336293643,"workplace":"b࿎mi","name":"¸","phone":"¢¦¤ª©"},{"id":1762336293644,"workplace":"bjmi˚","name":"¸","phone":"¢£ ¨±¤"},{"id":1762336293645,"workplace":"bjmilv","name":"¸","phone":"  ¤¨²ª"},{"id":1762336293646,"workplace":"bjmilv","name":"¸","phone":"¢§¡­£"},{"id":1762336293647,"workplace":"bjmil","name":"¸","phone":"¢¨¡¯£"},{"id":1762336293648,"workplace":"bjmilv","name":"¸","phone":"¥©¤®¥"},{"id":1762336293649,"workplace":"bjmilv","name":"¸","phone":"¢£ ¤±§"},{"id":1762336293650,"workplace":"bjmiȬ","name":"¸","phone":"¢¨¤²¥"},{"id":1762336293651,"workplace":"bjmiѫ","name":"¸","phone":"¢£¡ ±¬"},{"id":1762336293652,"workplace":"bjmࠧl","name":"¸","phone":"¢¨¡°£"},{"id":1762336293653,"workplace":"bjmilv","name":"¸","phone":"¢©£²¨"},{"id":1762336293654,"workplace":"bǧ촘","name":"¸","phone":"¢£ ¨±¥"},{"id":1762336293655,"workplace":"ǜԣmi","name":"¸","phone":"¢¨¡°£"},{"id":1762336293656,"workplace":"bǧmil","name":"¸","phone":" ¨¤ª£"},{"id":1762336293657,"workplace":"bТmil","name":"¸","phone":"¢§¡°§"},{"id":1762336293658,"workplace":"bj֓ɫ","name":"¸","phone":"¢©§ª¬"},{"id":1762336293659,"workplace":"bjmi","name":"¸","phone":"¢£¡ ±¨"},{"id":1762336293660,"workplace":"bjƮś","name":"¸","phone":"¢£§«©"},{"id":1762336293661,"workplace":"bjmi","name":"¸","phone":"¢¤¥©¤"},{"id":1762336293662,"workplace":"bjmilv","name":"¸","phone":"  ¤¨²©"},{"id":1762336293664,"workplace":"bjmilv","name":"¸","phone":"¥©¡¤­¬"},{"id":1762336293665,"workplace":"bjmiՑ","name":"¸","phone":"¢£ ¤±©"},{"id":1762336293666,"workplace":"bjmilv","name":"¸","phone":"¢§¢¯¦"},{"id":1762336293667,"workplace":"bĬmil","name":"¸","phone":"¢¦¤«¬"},{"id":1762336293668,"workplace":"bjmilv","name":"¸","phone":"¢¤«¨"},{"id":1762336293669,"workplace":"bjmil","name":"¸","phone":"¢©§ª¥"},{"id":1762336293670,"workplace":"bjmilv","name":"¸","phone":"¢¨¨¯§"},{"id":1762336293671,"workplace":"bjmilv","name":"¸","phone":" ¨¢°«"},{"id":1762336293672,"workplace":"҉Ҏmi","name":"¸","phone":"  ¥¨±£"},{"id":1762336293673,"workplace":"bjm˧l","name":"¸","phone":"¥©¢®¦"},{"id":1762336293674,"workplace":"bj̔","name":"¸","phone":"¥©¢®ª"},{"id":1762336293675,"workplace":"Νjmʖ","name":"¸","phone":"¢§¡¬¬"},{"id":1762336293676,"workplace":"bjmilv","name":"¸","phone":"¥ ¡©©"},{"id":1762336293677,"workplace":"bjmilv","name":"¸","phone":"¢£ ¨²©"},{"id":1762336293678,"workplace":"bjmࠣl","name":"¸","phone":"¥©¡§°«"},{"id":1762336293679,"workplace":"bjmilv","name":"¸","phone":"¢¦¡ ª«"},{"id":1762336293680,"workplace":"bjخil","name":"¸","phone":"¢¨¤²¥"},{"id":1762336293681,"workplace":"bjmilv","name":"¸","phone":"¢¨¤²©"},{"id":1762336293682,"workplace":"bjmi","name":"¸","phone":"¢£§ª§"},{"id":1762336293683,"workplace":"bjmilv","name":"¸","phone":" ¨¨®¥"},{"id":1762336293684,"workplace":"bjmקl","name":"¸","phone":"¢¨¤²©"},{"id":1762336293685,"workplace":"bjmilv","name":"¸","phone":"¢©¢®¬"},{"id":1762336293686,"workplace":"bjәţ","name":"¸","phone":"¥©¡§°¥"},{"id":1762336293687,"workplace":"bjmil","name":"¸","phone":"¢¦¡ ª¥"},{"id":1762336293688,"workplace":"ᱜｗ","name":"¸","phone":"¢¨¤²£"},{"id":1762336293689,"workplace":"bǡmil","name":"¸","phone":"¢¦¡ ª¬"},{"id":1762336293690,"workplace":"bۡmi","name":"¸","phone":"¢¨¡°«"},{"id":1762336293691,"workplace":"bȞm","name":"¸","phone":"¢¨¡¯©"},{"id":1762336293692,"workplace":"ͣjɩi","name":"¸","phone":"¢¦¤«¦"},{"id":1762336293694,"workplace":"ĢjmiÌ","name":"¸","phone":"¢£¡ ±«"},{"id":1762336293695,"workplace":"ԛjmil","name":"¸","phone":"¢¤¢®ª"},{"id":1762336293696,"workplace":"ǜjmʦ","name":"¸","phone":"¥ ¡©¬"},{"id":1762336293697,"workplace":"bjmilv","name":"¸","phone":"¢£¡ ±©"},{"id":1762336293698,"workplace":"bjmilv","name":"¸","phone":"¢§¢¯¥"},{"id":1762336293699,"workplace":"bjmħl","name":"¸","phone":"¢£¡ ±£"},{"id":1762336293700,"workplace":"Μjm","name":"¸","phone":"  ¦®§"},{"id":1762336293701,"workplace":"bj²il","name":"¸","phone":"¢©§ªª"},{"id":1762336293702,"workplace":"bՒ","name":"¸","phone":"¥©¡¤®¬"},{"id":1762336293703,"workplace":"bjmilv","name":"¸","phone":"¢£¥²©"},{"id":1762336293704,"workplace":"bjmilv","name":"¸","phone":"¢§¡°«"},{"id":1762336293705,"workplace":"bjѬ","name":"¸","phone":"¥©¡¤®«"},{"id":1762336293706,"workplace":"bjʪ","name":"¸","phone":"¢£¥±£"},{"id":1762336293707,"workplace":"bjmilv","name":"¸","phone":"¢¦¡«£"},{"id":1762336293708,"workplace":"bjmi͝","name":"¸","phone":"¢¥¡²©"},{"id":1762336293709,"workplace":"bj֚il","name":"¸","phone":" ¨¤ª£"},{"id":1762336293710,"workplace":"bjmilv","name":"¸","phone":"¢¥¤±«"},{"id":1762336293711,"workplace":"Ҡjm","name":"¸","phone":"¥©¤§¬£"},{"id":1762336293712,"workplace":"bjРil","name":"¸","phone":"¢©¤®©"},{"id":1762336293713,"workplace":"bjmil","name":"¸","phone":"¢¦¡«©"},{"id":1762336293714,"workplace":"bjmȨ","name":"¸","phone":"¢£¥±ª"},{"id":1762336293715,"workplace":"bjmilv","name":"¸","phone":"¢¨¤²¨"},{"id":1762336293716,"workplace":"bjmilv","name":"¸","phone":"¢£¥°¨"},{"id":1762336293717,"workplace":"bǧ鳖","name":"¸","phone":"¢¤¦©¤"},{"id":1762336293718,"workplace":"bjmilv","name":"¸","phone":"¥¨£°§"},{"id":1762336293719,"workplace":"bjߧi","name":"¸","phone":"¢£¢¯¥"},{"id":1762336293720,"workplace":"bjաil","name":"¸","phone":"¢¤«£"},{"id":1762336293721,"workplace":"bjmilv","name":"¸","phone":"¢§¡®¤"},{"id":1762336293722,"workplace":"bjmilv","name":"¸","phone":"¢©§ª£"},{"id":1762336293724,"workplace":"bjmilv","name":"¸","phone":"¢¥¥¡²©"},{"id":1762336293725,"workplace":"bjmilv","name":"¸","phone":"¢§¥£ª¤"},{"id":1762336293726,"workplace":"Ӌjm","name":"¸","phone":"¢¥§«£"},{"id":1762336293727,"workplace":"bjخil","name":"¸","phone":"¢¤­§"},{"id":1762336293728,"workplace":"bjm繨","name":"¸","phone":"¢¨¤²¬"},{"id":1762336293729,"workplace":"bjmilv","name":"¸","phone":"¢¨¡°¥"},{"id":1762336293730,"workplace":"bjm๨","name":"¸","phone":"¥©¤§¬©"},{"id":1762336293731,"workplace":"b⿐mi","name":"¸","phone":"¢£¦ª¬"},{"id":1762336293732,"workplace":"bȞm","name":"¸","phone":"¢¡¤²£"},{"id":1762336293733,"workplace":"؈jmil","name":"¸","phone":"¢¤­¬"},{"id":1762336293734,"workplace":"bꀟ","name":"¸","phone":"¥©¡§°¬"},{"id":1762336293735,"workplace":"bjmilv","name":"¸","phone":"¢£¡¡©¥"},{"id":1762336293736,"workplace":"đjmil","name":"¸","phone":"¢£¦ª¤"},{"id":1762336293737,"workplace":"bࠤmil","name":"¸","phone":"¢¨¡°¨"},{"id":1762336293738,"workplace":"bjmilv","name":"¸","phone":"¢©£²ª"},{"id":1762336293739,"workplace":"bjmil","name":"¸","phone":"¢¨¤²«"},{"id":1762336293740,"workplace":"bjmilv","name":"¸","phone":"¢©¢®¦"},{"id":1762336293741,"workplace":"bjخil","name":"¸","phone":"¢§¢¬¬"},{"id":1762336293742,"workplace":"bjmilv","name":"¸","phone":"¢¨¤²¬"},{"id":1762336293743,"workplace":"bࠧmil","name":"¸","phone":"¢©£²«"},{"id":1762336293744,"workplace":"bjm潖","name":"¸","phone":"¥©¡§°¨"},{"id":1762336293745,"workplace":"̜jmՎ","name":"¸","phone":"¢¤¢®£"},{"id":1762336293746,"workplace":"bjm","name":"¸","phone":"¢¨£°«"},{"id":1762336293747,"workplace":"bjmilv","name":"¸","phone":"¢¤¥©£"},{"id":1762336293748,"workplace":"bjmil","name":"¸","phone":"¢£¦ª¥"},{"id":1762336293749,"workplace":"bjmilv","name":"¸","phone":"¥©¡§°£"},{"id":1762336293750,"workplace":"bjmilv","name":"¸","phone":"¢§¥£ª¥"},{"id":1762336293751,"workplace":"b̥mʔ","name":"¸","phone":"¢§¢¬£"},{"id":1762336293752,"workplace":"bjґil","name":"¸","phone":"¢¤®¤"},{"id":1762336293754,"workplace":"bġmil","name":"¸","phone":"¢¤¦©£"},{"id":1762336293755,"workplace":"bjmilv","name":"¸","phone":"¥©¡§°¥"},{"id":1762336293756,"workplace":"פjmil","name":"¸","phone":"¢©£²£"},{"id":1762336293757,"workplace":"bjmilv","name":"¸","phone":"¥©¤§¬£"},{"id":1762336293758,"workplace":"bjmiŦ","name":"¸","phone":"¢£ ¤±ª"},{"id":1762336293759,"workplace":"bĦmil","name":"¸","phone":" ¨¬«"},{"id":1762336293760,"workplace":"bΦmil","name":"¸","phone":"¢£¥±ª"},{"id":1762336293761,"workplace":"bjґil","name":"¸","phone":"¥©¤®§"},{"id":1762336293762,"workplace":"bjmi֬","name":"¸","phone":"¢£¥²¦"},{"id":1762336293763,"workplace":"bjmiȫ","name":"¸","phone":"¢§¡®¤"},{"id":1762336293764,"workplace":"b՞mil","name":"¸","phone":"¢§¡°¬"},{"id":1762336293765,"workplace":"٤jmil","name":"¸","phone":"¢¨¡°¤"},{"id":1762336293766,"workplace":"bjmħl","name":"¸","phone":"¢¨£°«"},{"id":1762336293767,"workplace":"bǫm","name":"¸","phone":"¢¡¤¨«¤"},{"id":1762336293768,"workplace":"bjmĩl","name":"¸","phone":"¢£¥°£"},{"id":1762336293769,"workplace":"bȧmȨ","name":"¸","phone":"¢¤­ª"},{"id":1762336293770,"workplace":"bĨmil","name":"¸","phone":"¢§¤©£"},{"id":1762336293771,"workplace":"bj佦","name":"¸","phone":"¥©§ª«"},{"id":1762336293772,"workplace":"bĨmi","name":"¸","phone":"¢¨¤²¬"},{"id":1762336293773,"workplace":"bjmilv","name":"¸","phone":"¢©£²¨"},{"id":1762336293774,"workplace":"bj̧i","name":"¸","phone":"¢£§«¬"},{"id":1762336293775,"workplace":"bj֤il","name":"¸","phone":"¥ ¡©«"},{"id":1762336293776,"workplace":"bjխil","name":"¸","phone":"¢¨¡°¨"},{"id":1762336293777,"workplace":"bjmilv","name":"¸","phone":"¢§¡®£"},{"id":1762336293778,"workplace":"bjmilv","name":"¸","phone":"¢©£²ª"},{"id":1762336293779,"workplace":"đjm","name":"¸","phone":"¢£¡ ±«"},{"id":1762336293780,"workplace":"bjmil","name":"¸","phone":"¢£§«§"},{"id":1762336293781,"workplace":"bjmilv","name":"¸","phone":"¢¦¤ª£"},{"id":1762336293783,"workplace":"bjmilv","name":"¸","phone":"¢§¥©¨"},{"id":1762336293784,"workplace":"ϔjm","name":"¸","phone":"¢©¤®«"},{"id":1762336293785,"workplace":"bjmi","name":"¸","phone":"¢¤£¬ª"},{"id":1762336293786,"workplace":"bjmi˜","name":"¸","phone":"¢§¡®¬"},{"id":1762336293787,"workplace":"bjmil","name":"¸","phone":"¢¨¡°£"},{"id":1762336293788,"workplace":"bjmilv","name":"¸","phone":"¢¤²£"},{"id":1762336293789,"workplace":"bࠪmil","name":"¸","phone":"¢£¦ªª"},{"id":1762336293790,"workplace":"Μjmil","name":"¸","phone":" ©¦¯§"},{"id":1762336293791,"workplace":"bjәil","name":"¸","phone":"¢£§«¤"},{"id":1762336293792,"workplace":"b؞mi","name":"¸","phone":"¥©§ª©"},{"id":1762336293793,"workplace":"bjmilv","name":"¸","phone":"¢©¤®¬"},{"id":1762336293794,"workplace":"bjmiɚ","name":"¸","phone":"¢¨¡°«"},{"id":1762336293795,"workplace":"bjmi","name":"¸","phone":"¢¤£¬¦"},{"id":1762336293796,"workplace":"bjmil","name":"¸","phone":"¢§¥°£"},{"id":1762336293797,"workplace":"bjĭ","name":"¸","phone":"¥©¢®¥"},{"id":1762336293798,"workplace":"bjmil","name":"¸","phone":"¢£¡ ±£"},{"id":1762336293799,"workplace":"bjmilv","name":"¸","phone":"¥ §®©"},{"id":1762336293800,"workplace":"bjmiП","name":"¸","phone":"¢¨¤²«"},{"id":1762336293801,"workplace":"bȣmil","name":"¸","phone":"¢¨¡°¨"},{"id":1762336293802,"workplace":"đjmil","name":"¸","phone":"¢¨¤²¤"},{"id":1762336293803,"workplace":"bĤmȩ","name":"¸","phone":"¢§¡¬£"},{"id":1762336293804,"workplace":"bjmɧl","name":"¸","phone":"¢©¢®§"},{"id":1762336293805,"workplace":"bjmԢl","name":"¸","phone":"¢©§ª©"},{"id":1762336293806,"workplace":"؈jڮi","name":"¸","phone":" ¥¡§«¦"},{"id":1762336293807,"workplace":"bjmilv","name":"¸","phone":"¢©§ª¨"},{"id":1762336293808,"workplace":"bjәՎ","name":"¸","phone":"¢¨¡°¬"},{"id":1762336293810,"workplace":"bjmiʩ","name":"¸","phone":"¢§¤©¤"},{"id":1762336293811,"workplace":"bjmilv","name":"¸","phone":"¢£¥²¨"},{"id":1762336293812,"workplace":"bjm鸗","name":"¸","phone":"¥© §±ª"},{"id":1762336293813,"workplace":"bjmףl","name":"¸","phone":"¥©¢®¬"},{"id":1762336293814,"workplace":"bjؤil","name":"¸","phone":"¢§¡®«"},{"id":1762336293815,"workplace":"bjmilv","name":"¸","phone":"¢£ª£"},{"id":1762336293816,"workplace":"bjʪil","name":"¸","phone":"¢§¢¯¥"},{"id":1762336293817,"workplace":"bjŧil","name":"¸","phone":"¢¤¢®¨"},{"id":1762336293818,"workplace":"bjmƠl","name":"¸","phone":"¢§¢¯¨"},{"id":1762336293819,"workplace":"bjmi","name":"¸","phone":"¢£¦ª¦"},{"id":1762336293820,"workplace":"bjmilv","name":"¸","phone":"¢£ ¤±©"},{"id":1762336293821,"workplace":"bjmiȩ","name":"¸","phone":"¢£¢¯«"},{"id":1762336293822,"workplace":"bjmilv","name":"¸","phone":"¢©¡±¬"},{"id":1762336293823,"workplace":"bjm՝l","name":"¸","phone":"¢§¡®«"},{"id":1762336293824,"workplace":"bjґil","name":"¸","phone":"¢£§ª¦"},{"id":1762336293825,"workplace":"bjŧil","name":"¸","phone":"¢£¥²¬"},{"id":1762336293826,"workplace":"bjmi¿","name":"¸","phone":"¥©£²¨"},{"id":1762336293827,"workplace":"bȧmil","name":"¸","phone":"¢§¡¬ª"},{"id":1762336293828,"workplace":"bjmi֚","name":"¸","phone":"¢¦¤««"},{"id":1762336293829,"workplace":"bjmilv","name":"¸","phone":"¢©§ª©"},{"id":1762336293830,"workplace":"bjmilv","name":"¸","phone":"¢§¡¬¥"},{"id":1762336293831,"workplace":"bjmi","name":"¸","phone":"¢©§ª¨"},{"id":1762336293832,"workplace":"bjmilv","name":"¸","phone":"¢¤²©"},{"id":1762336293833,"workplace":"bjmilv","name":"¸","phone":"¢£¡ ±¥"},{"id":1762336293834,"workplace":"bjmilv","name":"¸","phone":"¥©¡§°¨"},{"id":1762336293835,"workplace":"bjmilv","name":"¸","phone":"¢£¥±©"},{"id":1762336293837,"workplace":"bjmՎ","name":"¸","phone":"¢¨¡°¬"},{"id":1762336293838,"workplace":"bժmȨ","name":"¸","phone":"¢¨¡°¬"},{"id":1762336293839,"workplace":"bjmilv","name":"¸","phone":"¢¨¡°£"},{"id":1762336293840,"workplace":"b\udc28\udfaai","name":"¸","phone":"¥ ¡©£"},{"id":1762336293841,"workplace":"ҠjmȨ","name":"¸","phone":"¥©¡¤®©"},{"id":1762336293842,"workplace":"bjmilv","name":"¸","phone":"¢£¥°¥"},{"id":1762336293843,"workplace":"bjmilv","name":"¸","phone":"¢§¢¯¨"},{"id":1762336293844,"workplace":"bjm֧l","name":"¸","phone":"¥©¤®ª"},{"id":1762336293845,"workplace":"bjmilv","name":"¸","phone":"¢£¥°¦"},{"id":1762336293846,"workplace":"bjmħl","name":"¸","phone":"¢§¢¯¤"},{"id":1762336293847,"workplace":"bȧmil","name":"¸","phone":"¢£¡ ±©"},{"id":1762336293848,"workplace":"bjР","name":"¸","phone":"  ¥ª¬"},{"id":1762336293849,"workplace":"֑Нmi","name":"¸","phone":"¢¥¥¡²£"},{"id":1762336293850,"workplace":"bjmiՑ","name":"¸","phone":"¢¨¤²¥"},{"id":1762336293851,"workplace":"bjmԝl","name":"¸","phone":"¥©¡§°£"},{"id":1762336293852,"workplace":"bjmilv","name":"¸","phone":"¢¦ ­£"},{"id":1762336293853,"workplace":"b՞m","name":"¸","phone":"¢£¥²¦"},{"id":1762336293854,"workplace":"bjmiՑ","name":"¸","phone":" ¢¨°¤"},{"id":1762336293855,"workplace":"bj͞ƪ","name":"¸","phone":"¢£¡ ±£"},{"id":1762336293856,"workplace":"֑jmil","name":"¸","phone":"¢§¥°ª"},{"id":1762336293857,"workplace":"bjmil","name":"¸","phone":"¢§¥£ª¥"},{"id":1762336293858,"workplace":"bjmilv","name":"¸","phone":"¢£¦ª¬"},{"id":1762336293859,"workplace":"bjʘil","name":"¸","phone":"¢¤¡¡ª¨"},{"id":1762336293860,"workplace":"ЉjmȨ","name":"¸","phone":"¢¨¡°¨"},{"id":1762336293861,"workplace":"bjmilv","name":"¸","phone":"¢¨¡¯§"},{"id":1762336293862,"workplace":"bjmilv","name":"¸","phone":"¢¨¡°£"},{"id":1762336293863,"workplace":"bjmil","name":"¸","phone":"¢§¡¬¥"},{"id":1762336293865,"workplace":"bjmilv","name":"¸","phone":"¢£§ª£"},{"id":1762336293866,"workplace":"bjmi","name":"¸","phone":"¢¨¡°©"},{"id":1762336293867,"workplace":"đҚؖ","name":"¸","phone":"¢£¥°£"},{"id":1762336293868,"workplace":"bjգil","name":"¸","phone":"¢©§ª¬"},{"id":1762336293869,"workplace":"bjmil","name":"¸","phone":" ¨¨®¥"},{"id":1762336293870,"workplace":"bjґil","name":"¸","phone":"¢¤«¤"},{"id":1762336293871,"workplace":"bjmilv","name":"¸","phone":"¢¨¡°«"},{"id":1762336293872,"workplace":"bjmi","name":"¸","phone":"¥¨¦¯¬"},{"id":1762336293873,"workplace":"bjmilv","name":"¸","phone":"¢§¡­¨"},{"id":1762336293874,"workplace":"bjmͫl","name":"¸","phone":"¢©¢®¥"},{"id":1762336293875,"workplace":"bjmi","name":"¸","phone":"¢¤¡¡ª§"},{"id":1762336293876,"workplace":"bjmƪl","name":"¸","phone":"¢©¤®¬"},{"id":1762336293877,"workplace":"bǦmil","name":"¸","phone":" ¨¤ªª"},{"id":1762336293878,"workplace":"bࠦmՎ","name":"¸","phone":"¢£¥±¥"},{"id":1762336293879,"workplace":"ΜjĬi","name":"¸","phone":"¥©¡§°¥"},{"id":1762336293880,"workplace":"bةmil","name":"¸","phone":"¢¤£¬£"},{"id":1762336293881,"workplace":"bjmilv","name":"¸","phone":"¢§¥°©"},{"id":1762336293882,"workplace":"bjƮȩ","name":"¸","phone":"¢£¥²¦"},{"id":1762336293883,"workplace":"bjmil","name":"¸","phone":"¢§¥©§"},{"id":1762336293884,"workplace":"ǜjmil","name":"¸","phone":"¢¨¡°£"},{"id":1762336293885,"workplace":"bjmi","name":"¸","phone":"¢¤¢­«"},{"id":1762336293886,"workplace":"bjmi","name":"¸","phone":"¢¢¡¡¬£"},{"id":1762336293887,"workplace":"bjm","name":"¸","phone":"¢§¡®£"},{"id":1762336293888,"workplace":"bmi","name":"¸","phone":" ¨ª¥"},{"id":1762336293889,"workplace":"bjњil","name":"¸","phone":"¢£ ¨±«"},{"id":1762336293890,"workplace":"bjmդl","name":"¸","phone":"¢£§ª©"},{"id":1762336293891,"workplace":"bjґil","name":"¸","phone":"¢©¢®¨"},{"id":1762336293893,"workplace":"פjmՎ","name":"¸","phone":"¢£§«¬"},{"id":1762336293894,"workplace":"bjשil","name":"¸","phone":"¢©£²¬"},{"id":1762336293895,"workplace":"ԛjm","name":"¸","phone":"¥©¡§°¥"},{"id":1762336293896,"workplace":"bĨmil","name":"¸","phone":"¢¤£¬©"},{"id":1762336293897,"workplace":"bjmil","name":"¸","phone":"¥©¡§°«"},{"id":1762336293898,"workplace":"bjmilv","name":"¸","phone":"¢¦ ­«"},{"id":1762336293899,"workplace":"bޤmȩ","name":"¸","phone":"¢¨¡°£"},{"id":1762336293900,"workplace":"bjmilv","name":"¸","phone":" ¥¢¡²¦"},{"id":1762336293901,"workplace":"bjmilv","name":"¸","phone":"¢¨¡°£"},{"id":1762336293902,"workplace":"bmi","name":"¸","phone":"¢¨¡°¤"},{"id":1762336293903,"workplace":"bjmi","name":"¸","phone":" ¥¢¡²ª"},{"id":1762336293904,"workplace":"bjmilv","name":"¸","phone":"¢¨¡°£"},{"id":1762336293905,"workplace":"bjծѨ","name":"¸","phone":"¢©¤®¦"},{"id":1762336293906,"workplace":"Љjmil","name":"¸","phone":"¢§¡¬¨"},{"id":1762336293907,"workplace":"bjmҪl","name":"¸","phone":"¥©¡§°¬"},{"id":1762336293908,"workplace":"bĪmil","name":"¸","phone":"¥¨¢®«"},{"id":1762336293909,"workplace":"bjm˪l","name":"¸","phone":"¢©¢®¬"},{"id":1762336293910,"workplace":"bjР","name":"¸","phone":"¥¦¤§ª«"},{"id":1762336293911,"workplace":"bjmilv","name":"¸","phone":"¢§¡¬¦"},{"id":1762336293912,"workplace":"bjmiѫ","name":"¸","phone":"¢§¤©¨"},{"id":1762336293913,"workplace":"bjmiՑ","name":"¸","phone":"¢¦¤ª©"},{"id":1762336293914,"workplace":"bjґil","name":"¸","phone":"¥©¤§¬¦"},{"id":1762336293915,"workplace":"bΡmil","name":"¸","phone":"¢¤¢¬§"},{"id":1762336293916,"workplace":"bjmi","name":"¸","phone":"¥¨¡¬©"},{"id":1762336293917,"workplace":"bjѨՎ","name":"¸","phone":"¢¤ ­¦"},{"id":1762336293918,"workplace":"bjʪi","name":"¸","phone":"¢£¥²©"},{"id":1762336293920,"workplace":"bjmilv","name":"¸","phone":"¢£¥²¨"},{"id":1762336293921,"workplace":"bjmilv","name":"¸","phone":"¢§¢¯«"},{"id":1762336293922,"workplace":"bj֦il","name":"¸","phone":"¢£¥²£"},{"id":1762336293923,"workplace":"bjmi","name":"¸","phone":"¢£¢¯¬"},{"id":1762336293924,"workplace":"Ҡjm","name":"¸","phone":"¥©§ª£"},{"id":1762336293925,"workplace":"bjmilv","name":"¸","phone":"¢¨¡°£"},{"id":1762336293926,"workplace":"bjmilv","name":"¸","phone":"¥©§ª¤"},{"id":1762336293927,"workplace":"bīmil","name":"¸","phone":"¢©£²£"},{"id":1762336293928,"workplace":"bjmi","name":"¸","phone":"¢©§ª¤"},{"id":1762336293929,"workplace":"bj՘ɗ","name":"¸","phone":"¢§¡¬¥"},{"id":1762336293930,"workplace":"bjʘil","name":"¸","phone":"¢£¥²¤"},{"id":1762336293931,"workplace":"bjmilv","name":"¸","phone":"¥© §±ª"},{"id":1762336293932,"workplace":"bjӗil","name":"¸","phone":"¢£¥²ª"},{"id":1762336293933,"workplace":"bȧmi","name":"¸","phone":"¢¤²¥"},{"id":1762336293934,"workplace":"Ҡƫ͞","name":"¸","phone":"¢§¡®«"},{"id":1762336293935,"workplace":"bjmi","name":"¸","phone":"¥©¡§°£"},{"id":1762336293936,"workplace":"bՠmil","name":"¸","phone":"¥ ¡©ª"},{"id":1762336293937,"workplace":"bjmilv","name":"¸","phone":"¢©§ª¥"},{"id":1762336293938,"workplace":"bjРil","name":"¸","phone":"¢¤¢®¨"},{"id":1762336293939,"workplace":"bjmilv","name":"¸","phone":"¢¨¡°«"},{"id":1762336293940,"workplace":"҉jmil","name":"¸","phone":"¢¤««"},{"id":1762336293941,"workplace":"bjmilv","name":"¸","phone":"¥©¡¤®£"},{"id":1762336293942,"workplace":"bjmi","name":"¸","phone":"¢©§ª¤"},{"id":1762336293943,"workplace":"bjmilv","name":"¸","phone":"¢§¥°§"},{"id":1762336293944,"workplace":"bĩmil","name":"¸","phone":"¢£§«¬"},{"id":1762336293946,"workplace":"bjmilv","name":"¸","phone":"¢©£²«"},{"id":1762336293947,"workplace":"đjmil","name":"¸","phone":"¢£§«©"},{"id":1762336293948,"workplace":"bĢġi","name":"¸","phone":"¢§¢¯¨"},{"id":1762336293949,"workplace":"bjmilv","name":"¸","phone":"¢£¡ ±ª"},{"id":1762336293950,"workplace":"bjmi","name":"¸","phone":"¢¤¡¡ª¥"},{"id":1762336293951,"workplace":"bСmǛ","name":"¸","phone":"¢¥¥¡²¥"},{"id":1762336293952,"workplace":"bjmilv","name":"¸","phone":"¢¤¢®¤"},{"id":1762336293953,"workplace":"bjmĝl","name":"¸","phone":"¥©§ª¨"},{"id":1762336293954,"workplace":"bjmilv","name":"¸","phone":"¢©£²ª"},{"id":1762336293955,"workplace":"ԋjͩi","name":"¸","phone":"¢¨¤²¬"},{"id":1762336293956,"workplace":"bjmilv","name":"¸","phone":"¥¨£²§"},{"id":1762336293957,"workplace":"bjmﺧ","name":"¸","phone":"¢£¡ ±¨"},{"id":1762336293958,"workplace":"؈իmi","name":"¸","phone":"¢§¥©©"},{"id":1762336293959,"workplace":"b˧mil","name":"¸","phone":"¢§¤©¬"},{"id":1762336293960,"workplace":"bjmi","name":"¸","phone":"¥©¡§°¥"},{"id":1762336293961,"workplace":"bjmi","name":"¸","phone":"¢¦ ­©"},{"id":1762336293962,"workplace":"bjґȨ","name":"¸","phone":"¢¦¤«¬"},{"id":1762336293963,"workplace":"bjmil","name":"¸","phone":" ©§«¤"},{"id":1762336293964,"workplace":"bjmiȫ","name":"¸","phone":"¢¨£°¬"},{"id":1762336293965,"workplace":"bĪmil","name":"¸","phone":"¢¨¡°¤"},{"id":1762336293966,"workplace":"bjmilv","name":"¸","phone":"¥©¡¤®©"},{"id":1762336293967,"workplace":"bjmʣl","name":"¸","phone":"¢©¢®£"},{"id":1762336293968,"workplace":"bjӗil","name":"¸","phone":"¢¤¡¡ª¦"},{"id":1762336293969,"workplace":"Μjmʔ","name":"¸","phone":"¢¤­ª"},{"id":1762336293970,"workplace":"bĠmil","name":"¸","phone":"  ¥ª£"},{"id":1762336293972,"workplace":"bȨm","name":"¸","phone":"¢£¦ª¤"},{"id":1762336293973,"workplace":"bjmilv","name":"¸","phone":"¢£¥±¦"},{"id":1762336293974,"workplace":"bjmiѫ","name":"¸","phone":"¢§¢¯¤"},{"id":1762336293975,"workplace":"bjРɫ","name":"¸","phone":"¢¨¡°£"},{"id":1762336293976,"workplace":"bjmi","name":"¸","phone":"¢¤¢¬£"},{"id":1762336293977,"workplace":"bǥmil","name":"¸","phone":"¢©£²¨"},{"id":1762336293978,"workplace":"؈jm","name":"¸","phone":"¢¨¡¯£"},{"id":1762336293979,"workplace":"bjmilv","name":"¸","phone":"¢©£²«"},{"id":1762336293980,"workplace":"bjmilv","name":"¸","phone":"¢§¥£ª£"},{"id":1762336293981,"workplace":"bjŧil","name":"¸","phone":"¢©¤®«"},{"id":1762336293982,"workplace":"bjmilv","name":"¸","phone":"¢¨¤²¬"},{"id":1762336293983,"workplace":"bןmil","name":"¸","phone":"¢©£²§"},{"id":1762336293984,"workplace":"bjmilv","name":"¸","phone":"¢£ ¨±£"},{"id":1762336293985,"workplace":"bjخil","name":"¸","phone":"¢§¡°¦"},{"id":1762336293986,"workplace":"Əͦmi","name":"¸","phone":" ©¦¯©"},{"id":1762336293987,"workplace":"bjmiՑ","name":"¸","phone":"¢¤²«"},{"id":1762336293988,"workplace":"bjmilv","name":"¸","phone":" ©§««"},{"id":1762336293989,"workplace":"bjmڣl","name":"¸","phone":"¢£¥±§"},{"id":1762336293990,"workplace":"b͠mil","name":"¸","phone":"¥©¤®¬"},{"id":1762336293991,"workplace":"bjmilv","name":"¸","phone":"¢¨¤²¥"},{"id":1762336293992,"workplace":"bjmilv","name":"¸","phone":"¢£¡ ±©"},{"id":1762336293993,"workplace":"bjґil","name":"¸","phone":"¢©¢®«"},{"id":1762336293994,"workplace":"bjmңl","name":"¸","phone":"¢§¡®¤"},{"id":1762336293995,"workplace":"bmi","name":"¸","phone":"¢§¡®ª"},{"id":1762336293996,"workplace":"bjmil","name":"¸","phone":"¢¦­¬"},{"id":1762336293998,"workplace":"bjґil","name":"¸","phone":"¢©¤²¥"},{"id":1762336293999,"workplace":"bjmiʪ","name":"¸","phone":"¢¨¤²¤"},{"id":1762336294000,"workplace":"bjmi","name":"¸","phone":"¢§¡­§"},{"id":1762336294001,"workplace":"bjmil","name":"¸","phone":"¢¨¤²£"},{"id":1762336294002,"workplace":"bjmilv","name":"¸","phone":"¥©£²¬"},{"id":1762336294003,"workplace":"bjmilv","name":"¸","phone":"¢¨¡¯©"},{"id":1762336294004,"workplace":"bjmilv","name":"¸","phone":" ©¤­¦"},{"id":1762336294005,"workplace":"bjmi","name":"¸","phone":"¢ £§¯©"},{"id":1762336294006,"workplace":"bjmilv","name":"¸","phone":"¢¦­¤"},{"id":1762336294007,"workplace":"bjґil","name":"¸","phone":"¢¦ ­ª"},{"id":1762336294008,"workplace":"Ҡjmil","name":"¸","phone":"¢£¡ ±¦"},{"id":1762336294009,"workplace":"bТĭi","name":"¸","phone":"¥¦£¥­©"},{"id":1762336294010,"workplace":"bj͞il","name":"¸","phone":"¢¨¤²£"},{"id":1762336294011,"workplace":"bبߡi","name":"¸","phone":"¥©¤§¬¥"},{"id":1762336294012,"workplace":"bjޯ","name":"¸","phone":"¢©¢®¨"},{"id":1762336294013,"workplace":"bjmilv","name":"¸","phone":"¢§¢¯¤"},{"id":1762336294014,"workplace":"bjؕȨ","name":"¸","phone":" ¨¨®©"},{"id":1762336294015,"workplace":"bjmilv","name":"¸","phone":"¥©¡§°¤"},{"id":1762336294016,"workplace":"bjmilv","name":"¸","phone":"  ¨°«"},{"id":1762336294017,"workplace":"bĦm֠","name":"¸","phone":"¢§¡®¤"},{"id":1762336294018,"workplace":"bjmil","name":"¸","phone":"¢¤«¤"},{"id":1762336294019,"workplace":"bjmilv","name":"¸","phone":"¢¨£°¤"},{"id":1762336294020,"workplace":"Ҡjmʔ","name":"¸","phone":"¢§¡®£"},{"id":1762336294021,"workplace":"b٨mȩ","name":"¸","phone":"¢¦¡ ªª"},{"id":1762336294022,"workplace":"bjmilv","name":"¸","phone":"¢¨¡°«"},{"id":1762336294023,"workplace":"bjҒٔ","name":"¸","phone":"¢£¥°©"},{"id":1762336294025,"workplace":"bjmi","name":"¸","phone":"¢©£²«"},{"id":1762336294026,"workplace":"bjmѨ","name":"¸","phone":"¢¦¤ª«"},{"id":1762336294027,"workplace":"bjmilv","name":"¸","phone":"¥¨£¬£"},{"id":1762336294028,"workplace":"bjخil","name":"¸","phone":"¢ ¢§ª¤"},{"id":1762336294029,"workplace":"bjmilv","name":"¸","phone":"¢£¡ ±¤"},{"id":1762336294030,"workplace":"bjȬ","name":"¸","phone":"¢¨¡°«"},{"id":1762336294031,"workplace":"bjա","name":"¸","phone":" ¥¡§«£"},{"id":1762336294032,"workplace":"bjmilv","name":"¸","phone":"¢£¡ ±£"},{"id":1762336294033,"workplace":"bjmi","name":"¸","phone":"¢£¡ ±¤"},{"id":1762336294034,"workplace":"b֧mil","name":"¸","phone":"¢§¥©«"},{"id":1762336294035,"workplace":"bmi","name":"¸","phone":"¢¨¡°£"},{"id":1762336294036,"workplace":"bէmi","name":"¸","phone":"¥©¢®¦"},{"id":1762336294037,"workplace":"Ҡjmil","name":"¸","phone":"¥©¢®ª"},{"id":1762336294038,"workplace":"bjґՏ","name":"¸","phone":"¢¦¡ ª£"},{"id":1762336294039,"workplace":"bjәil","name":"¸","phone":"¥©§ª¬"},{"id":1762336294040,"workplace":"bΦmil","name":"¸","phone":"¢¨£°«"},{"id":1762336294041,"workplace":"bjmilv","name":"¸","phone":"¥ ¡©¨"},{"id":1762336294042,"workplace":"bئmil","name":"¸","phone":"¢¨¤²¤"},{"id":1762336294043,"workplace":"bjmϣl","name":"¸","phone":"¢£¥²«"},{"id":1762336294045,"workplace":"bjmiȫ","name":"¸","phone":"¢©¤®ª"},{"id":1762336294046,"workplace":"bjґȩ","name":"¸","phone":"¢¨¡°¬"},{"id":1762336294047,"workplace":"bȠmЍ","name":"¸","phone":"¢§¢¬©"},{"id":1762336294048,"workplace":"bjmilv","name":"¸","phone":"¢©£²¤"},{"id":1762336294049,"workplace":"bjmilv","name":"¸","phone":"¢§¢¯¤"},{"id":1762336294051,"workplace":"bjʪՎ","name":"¸","phone":" ¨¨²¥"},{"id":1762336294052,"workplace":"bjm㽖","name":"¸","phone":"¢©¡°«"},{"id":1762336294053,"workplace":"bjmiȬ","name":"¸","phone":" ¨¬©"},{"id":1762336294054,"workplace":"bjmilv","name":"¸","phone":"¢¨¨¯¥"},{"id":1762336294055,"workplace":"bjmil","name":"¸","phone":"¢¤©©"},{"id":1762336294056,"workplace":"bةϧi","name":"¸","phone":"¢¦¡ ª§"},{"id":1762336294057,"workplace":"bjmilv","name":"¸","phone":" ¥¤¡°©"},{"id":1762336294058,"workplace":"bjmࠧl","name":"¸","phone":"¢¨¡°¬"},{"id":1762336294059,"workplace":"bjmi","name":"¸","phone":"¢¤¦©¦"},{"id":1762336294060,"workplace":"bjmilv","name":"¸","phone":"¢¨¡°¤"},{"id":1762336294061,"workplace":"bjՖil","name":"¸","phone":"¥©¡§°¨"},{"id":1762336294062,"workplace":"bjmiŞ","name":"¸","phone":"¢¨¡°¥"},{"id":1762336294063,"workplace":"bjmilv","name":"¸","phone":"¢©¢®¨"},{"id":1762336294064,"workplace":"bȦmil","name":"¸","phone":"¢£¥²¤"},{"id":1762336294065,"workplace":"bjmil","name":"¸","phone":"¥©¡¤®¦"},{"id":1762336294066,"workplace":"bjmi","name":"¸","phone":"¢©£²£"},{"id":1762336294067,"workplace":"bjmilv","name":"¸","phone":"¢¦®©"},{"id":1762336294068,"workplace":"bjґil","name":"¸","phone":"¢¤®¤"},{"id":1762336294069,"workplace":"bjŧil","name":"¸","phone":" ©§«©"},{"id":1762336294070,"workplace":"bĪmil","name":"¸","phone":" ©¤®¬"},{"id":1762336294071,"workplace":"bjmiʚ","name":"¸","phone":" ©£¥©«"},{"id":1762336294072,"workplace":"bjmiȬ","name":"¸","phone":"¢¨¨¯¬"},{"id":1762336294073,"workplace":"bjmi","name":"¸","phone":"¢§¢¯¥"},{"id":1762336294075,"workplace":"bjmil","name":"¸","phone":"¢£¦ª©"},{"id":1762336294076,"workplace":"bjmilv","name":"¸","phone":"¢¨¤²©"},{"id":1762336294077,"workplace":"bjmţ","name":"¸","phone":"¢¦¤«©"},{"id":1762336294078,"workplace":"bjґil","name":"¸","phone":"¢¨¤²«"},{"id":1762336294079,"workplace":"b͡mil","name":"¸","phone":"¢£¡ ±«"},{"id":1762336294080,"workplace":"bjmil","name":"¸","phone":"¢¤©©"},{"id":1762336294081,"workplace":"bjԫil","name":"¸","phone":"¢§¡¬¨"},{"id":1762336294082,"workplace":"bjmil","name":"¸","phone":"¢£¢¯¤"},{"id":1762336294083,"workplace":"bjmiɮ","name":"¸","phone":"¢©¤®ª"},{"id":1762336294084,"workplace":"bȩmΕ","name":"¸","phone":"¢£¥°«"},{"id":1762336294085,"workplace":"bjmilv","name":"¸","phone":"¥©§ª£"},{"id":1762336294086,"workplace":"bjm㽖","name":"¸","phone":"¢§¡®ª"},{"id":1762336294087,"workplace":"bjmilv","name":"¸","phone":"¢£¦ª¬"},{"id":1762336294088,"workplace":"bjmiʩ","name":"¸","phone":"¥ ¡©¦"},{"id":1762336294089,"workplace":"ǜjmil","name":"¸","phone":"¢£¥°£"},{"id":1762336294090,"workplace":"bjخil","name":"¸","phone":"¢£¡ °£"},{"id":1762336294091,"workplace":"bĨmil","name":"¸","phone":"¢¨¡°¨"},{"id":1762336294092,"workplace":"đjϪi","name":"¸","phone":"¢¦¤«¨"},{"id":1762336294093,"workplace":"bjmilv","name":"¸","phone":"¥¨£°£"},{"id":1762336294094,"workplace":"bmi","name":"¸","phone":"¢§¥©©"},{"id":1762336294095,"workplace":"bjmilv","name":"¸","phone":"¢£¥°£"},{"id":1762336294096,"workplace":"bj֚Վ","name":"¸","phone":"¢¨¤²¬"},{"id":1762336294097,"workplace":"bjmi","name":"¸","phone":"¢©£²¤"},{"id":1762336294098,"workplace":"bjmilv","name":"¸","phone":"¢¥¥¡©¥"},{"id":1762336294100,"workplace":"bjmi","name":"¸","phone":"¥©§ª£"},{"id":1762336294101,"workplace":"bjmilv","name":"¸","phone":"¢¤¢®¦"},{"id":1762336294102,"workplace":"bjmilv","name":"¸","phone":"¢¨£°¥"},{"id":1762336294103,"workplace":"bjmilv","name":"¸","phone":"¢¥¤±¥"},{"id":1762336294104,"workplace":"bࠤmil","name":"¸","phone":"¢©£²«"},{"id":1762336294105,"workplace":"b􌸧i","name":"¸","phone":"¢¤¡¡ª¬"},{"id":1762336294106,"workplace":"Ҡjߧi","name":"¸","phone":"¢©£¬¥"},{"id":1762336294107,"workplace":"bjmilv","name":"¸","phone":"¢¨¡°£"},{"id":1762336294108,"workplace":"bjmilv","name":"¸","phone":"¢©¢®©"},{"id":1762336294109,"workplace":"bjmi","name":"¸","phone":"¥©¤®¦"},{"id":1762336294110,"workplace":"bjmil","name":"¸","phone":"¢©¤®©"},{"id":1762336294111,"workplace":"bjmi","name":"¸","phone":"¢§¡°«"},{"id":1762336294112,"workplace":"bjmϣl","name":"¸","phone":"¢¦®¦"},{"id":1762336294113,"workplace":"bjmilv","name":"¸","phone":" ©¤®¨"},{"id":1762336294114,"workplace":"bjmilv","name":"¸","phone":"¢£¡ ±«"},{"id":1762336294115,"workplace":"bjmilv","name":"¸","phone":" ©¤¨©¨"},{"id":1762336294116,"workplace":"bj̫i","name":"¸","phone":"¢£¢¯¤"},{"id":1762336294117,"workplace":"bjȬ","name":"¸","phone":"¢©£²«"},{"id":1762336294118,"workplace":"bئmil","name":"¸","phone":"¥©¢®¦"},{"id":1762336294119,"workplace":"ʐjʢi","name":"¸","phone":"¢£ ¨²£"},{"id":1762336294120,"workplace":"bjmiɮ","name":"¸","phone":"¢§¡­£"},{"id":1762336294121,"workplace":"bjmilv","name":"¸","phone":"¢§¥©¤"},{"id":1762336294122,"workplace":"bjmiѫ","name":"¸","phone":"¢£ ¤±©"},{"id":1762336294123,"workplace":"bjmilv","name":"¸","phone":"¢§¡¬¤"},{"id":1762336294125,"workplace":"bjmȋ","name":"¸","phone":"¢£¥²ª"},{"id":1762336294126,"workplace":"bjmil","name":"¸","phone":"¥©¢®£"},{"id":1762336294127,"workplace":"bjmil","name":"¸","phone":" ¥¢¡²«"},{"id":1762336294128,"workplace":"bjmilv","name":"¸","phone":"¢£ ¤±¬"},{"id":1762336294129,"workplace":"bjȭil","name":"¸","phone":"¢©¤®£"}]